circuitbrew/__init__.py
circuitbrew/cb_netlist.py
circuitbrew/circuitbrew.py
circuitbrew/compound_ports.py
circuitbrew/elements.py
circuitbrew/fets.py
circuitbrew/gates.py
circuitbrew/helpers.py
circuitbrew/measure.py
circuitbrew/module.py
circuitbrew/ports.py
circuitbrew/qdi.py
circuitbrew/stack.py
circuitbrew/symbols.py
circuitbrew/test.py
circuitbrew/test2.py
circuitbrew/test3.py
circuitbrew/test4.py
circuitbrew/version.py
circuitbrew/walker.py
circuitbrew/examples/and.py
circuitbrew/examples/buf.py
circuitbrew/examples/buf_wchb.py
circuitbrew/examples/buf_wchb_chain.py
circuitbrew/examples/inv.py
circuitbrew/examples/inv_simple.py
circuitbrew/examples/parametrized.py
circuitbrew/examples/prs.py
circuitbrew/examples/simple.py
circuitbrew/examples/simple2.py
circuitbrew/examples/simple3.py
circuitbrew/examples/simple4.py
circuitbrew/examples/test.py
circuitbrew/examples/inverter/inverter_01.py
circuitbrew/examples/inverter/inverter_02.py
circuitbrew/examples/inverter/inverter_03.py
circuitbrew/examples/inverter/inverter_04.py
circuitbrew/examples/inverter/inverter_05.py
circuitbrew/examples/inverter_sim/inverter_sim_01.py
circuitbrew/examples/inverter_sim/inverter_sim_02.py
circuitbrew/examples/inverter_sim/inverter_sim_03.py
circuitbrew/examples/wchb/.gitignore
circuitbrew/examples/wchb/main.py
circuitbrew/examples/wchb/wchb_01.py
circuitbrew/examples/wchb/wchb_02.py
circuitbrew/examples/wchb/wchb_c2_01.py
circuitbrew/examples/wchb/wchb_inverter_01.py
circuitbrew/examples/wchb/wchb_nor2_01.py
circuitbrew/examples/wchb/wchb_nor2_02.py
circuitbrew/output/hspice_clk.va
circuitbrew/output/template_0_hspice_bucket.va
circuitbrew/output/template_0_hspice_src.va
circuitbrew/output/template_1_hspice_src.va
circuitbrew/output/top.sp
circuitbrew/tech/generic.sp
circuitbrew/tech/hspice_bucket.va
circuitbrew/tech/hspice_bucket_1of2.va
circuitbrew/tech/hspice_bucket_1of2_old.va
circuitbrew/tech/hspice_clk.va
circuitbrew/tech/hspice_src.va
circuitbrew/tech/hspice_src_1of2.va
circuitbrew-0.1.9.dist-info/METADATA
circuitbrew-0.1.9.dist-info/WHEEL
circuitbrew-0.1.9.dist-info/entry_points.txt
circuitbrew-0.1.9.dist-info/licenses/AUTHORS.rst
circuitbrew-0.1.9.dist-info/licenses/LICENSE
circuitbrew-0.1.9.dist-info/RECORD
