Metadata-Version: 2.1
Name: circuitbrew
Version: 0.1.9
Summary: Build SPICE circuits and simulation environments using Python
Project-URL: Homepage, https://virantha.github.io/circuitbrew
Project-URL: Repository, https://github.com/virantha/circuitbrew
Project-URL: Bug Tracker, https://github.com/virantha/circuitbrew/issues
Author-email: Virantha Ekanayake <virantha@gmail.com>
License-File: AUTHORS.rst
License-File: LICENSE
Keywords: circuits,spice
Classifier: License :: OSI Approved :: Apache Software License
Classifier: Operating System :: OS Independent
Classifier: Programming Language :: Python :: 3
Requires-Python: >=3.8
Requires-Dist: curio>=1.6
Requires-Dist: docopt-ng
Requires-Dist: mako
Requires-Dist: pyyaml>=6.0
Requires-Dist: schema
